fuzzypy/__init__.py
fuzzypy/defuzzification.py
fuzzypy/implications.py
fuzzypy/memberships.py
fuzzypy/variables.py
fuzzypy-1.0.1.dist-info/licenses/LICENSE
tests/Implication_test.py
tests/__init__.py
tests/defuzzify_test.py
tests/membership_functions_test.py
tests/variables_test.py
fuzzypy-1.0.1.dist-info/METADATA
fuzzypy-1.0.1.dist-info/WHEEL
fuzzypy-1.0.1.dist-info/top_level.txt
fuzzypy-1.0.1.dist-info/RECORD
