Metadata-Version: 2.4
Name: fuzzypy
Version: 1.0.1
Home-page: https://github.com/alsprogrammer/PythonFuzzyLogic
Author: Aleksandr Saiapin
Author-email: alstutor@gmail.com
License-File: LICENSE
Dynamic: author
Dynamic: author-email
Dynamic: description
Dynamic: home-page
Dynamic: license-file
